MANIFEST.in
README.md
requirements.txt
setup.cfg
setup.py
hudai/__init__.py
hudai/client.py
hudai/error.py
hudai.egg-info/PKG-INFO
hudai.egg-info/SOURCES.txt
hudai.egg-info/dependency_links.txt
hudai.egg-info/requires.txt
hudai.egg-info/top_level.txt
hudai/helpers/__init__.py
hudai/helpers/http_client.py
hudai/helpers/http_errors.py
hudai/helpers/resource.py
hudai/resources/__init__.py
hudai/resources/action_item.py
hudai/resources/article.py
hudai/resources/article_company.py
hudai/resources/article_geography.py
hudai/resources/article_highlights.py
hudai/resources/article_key_term.py
hudai/resources/article_person.py
hudai/resources/article_tag.py
hudai/resources/collateral.py
hudai/resources/company.py
hudai/resources/company_event.py
hudai/resources/company_industry.py
hudai/resources/company_key_term.py
hudai/resources/company_profile.py
hudai/resources/conference.py
hudai/resources/conference_speaker.py
hudai/resources/domain.py
hudai/resources/feed.py
hudai/resources/industry.py
hudai/resources/key_term.py
hudai/resources/model_score.py
hudai/resources/organization.py
hudai/resources/person.py
hudai/resources/person_key_term.py
hudai/resources/person_quote.py
hudai/resources/source.py
hudai/resources/stock_alert.py
hudai/resources/system_event.py
hudai/resources/system_task.py
hudai/resources/text_corpus.py
hudai/resources/tweets.py
hudai/resources/user.py
hudai/resources/user_company.py
hudai/resources/user_company_group.py
hudai/resources/user_contact.py
hudai/resources/user_digest_subscription.py
hudai/resources/user_key_term.py
hudai/resources/user_person.py
hudai/resources/user_source.py
hudai/resources/user_template.py
hudai/resources/video.py
hudai/resources/video_company.py
hudai/resources/video_person.py
test/test_client.py
test/test_resource.py