Metadata-Version: 1.1
Name: hudai
Version: 2.49.0
Summary: HUD.ai API python bindings
Home-page: https://github.com/FoundryAI/hud-ai-python
Author: HUD.ai Engineering
Author-email: engineering@hud.ai
License: MIT
Download-URL: https://github.com/FoundryAI/hud-ai-python/archive/2.49.0.tar.gz
Keywords: hud.ai,hudai,foundry.ai,foundrydc
Platform: UNKNOWN
Classifier: Development Status :: 3 - Alpha
Classifier: Intended Audience :: Developers
Classifier: Operating System :: OS Independent
Classifier: Programming Language :: Python
Classifier: Topic :: Software Development :: Build Tools
Classifier: License :: OSI Approved :: MIT License
Classifier: Programming Language :: Python
Classifier: Programming Language :: Python :: 2
Classifier: Programming Language :: Python :: 2.7
